gptservice/__init__.py
gptservice/apps.py
gptservice/Tools/__init__.py
gptservice/Tools/features/__init__.py
gptservice/Tools/features/aws_services.py
gptservice/Tools/features/bookmyshowscraper.py
gptservice/Tools/features/google_flights.py
gptservice/Tools/features/google_shopping.py
gptservice/Tools/services/__init__.py
gptservice/Tools/services/aws_svc.py
gptservice/Tools/services/bookmyshow.py
gptservice/Tools/services/features.py
gptservice/Tools/services/flights.py
gptservice/Tools/services/shopping.py
gptservice-0.1.4.dist-info/METADATA
gptservice-0.1.4.dist-info/WHEEL
gptservice-0.1.4.dist-info/entry_points.txt
gptservice-0.1.4.dist-info/top_level.txt
gptservice-0.1.4.dist-info/RECORD
