Metadata-Version: 2.1
Name: gptservice
Version: 0.1.4
Summary: GPT Assistant
Author: Sukamal Rakshit
Author-email: sukamalrksht77@email.com
Keywords: python,chatbot
Classifier: Development Status :: 3 - Alpha
Classifier: Intended Audience :: Education
Classifier: Programming Language :: Python :: 3
Classifier: Operating System :: POSIX :: Linux
Classifier: Operating System :: Microsoft :: Windows
Requires-Dist: boto3
Requires-Dist: serpapi
Requires-Dist: openai
Requires-Dist: google-search-results
